{
    "channelCode": "FPK",
    "channelSecret":"12345",
    "appVersionId": "V1.0",
    "publicKeys":"userId,saNo",
    "excludeConf": {
        "domains":["http://uat.fpk.bqjr.cn/orderInfo/list","baidu.com"]
    },
    "syncConf":{
        "requestDataConf": [
            {
                "url":"http://uat.fpk.bqjr.cn/orderInfo/getOrderStatusCount",
                "paramKeys":["saNo","heh"]
            }
        ]
    },
    "asyncConf":{
        "reportTime": "20",
        "reportVolume": "20"
    }
}